cogrid/__init__.py
cogrid/cogrid_env.py
cogrid/constants.py
cogrid/run_interactive.py
cogrid/run_state_demo.py
cogrid/test_gridworld.py
cogrid/test_gridworld_env.py
cogrid/test_overcooked_env.py
cogrid/core/__init__.py
cogrid/core/actions.py
cogrid/core/agent.py
cogrid/core/constants.py
cogrid/core/directions.py
cogrid/core/grid.py
cogrid/core/grid_object.py
cogrid/core/grid_utils.py
cogrid/core/layouts.py
cogrid/core/reward.py
cogrid/core/roles.py
cogrid/core/typing.py
cogrid/envs/__init__.py
cogrid/envs/registry.py
cogrid/envs/goal_seeking/__init__.py
cogrid/envs/goal_seeking/agent.py
cogrid/envs/goal_seeking/goal_seeking.py
cogrid/envs/overcooked/__init__.py
cogrid/envs/overcooked/agent.py
cogrid/envs/overcooked/overcooked.py
cogrid/envs/overcooked/overcooked_features.py
cogrid/envs/overcooked/overcooked_grid_objects.py
cogrid/envs/overcooked/overcooked_utils.py
cogrid/envs/overcooked/rewards.py
cogrid/envs/overcooked/test_state_serialization.py
cogrid/envs/search_rescue/__init__.py
cogrid/envs/search_rescue/rewards.py
cogrid/envs/search_rescue/search_rescue.py
cogrid/envs/search_rescue/search_rescue_grid_objects.py
cogrid/envs/search_rescue/search_rescue_tests.py
cogrid/envs/search_rescue/sr_utils.py
cogrid/envs/search_rescue/test_redvictim_serialization.py
cogrid/envs/search_rescue/test_sr_env_serialization.py
cogrid/envs/search_rescue/test_sr_objects_serialization.py
cogrid/feature_space/__init__.py
cogrid/feature_space/feature.py
cogrid/feature_space/feature_space.py
cogrid/feature_space/features.py
cogrid/scripts/__init__.py
cogrid/scripts/audit_serialization.py
cogrid/scripts/test_audit_serialization.py
cogrid/tests/__init__.py
cogrid/tests/test_determinism.py
cogrid/tests/test_serialization_integration.py
cogrid/visualization/__init__.py
cogrid/visualization/rendering.py
cogrid-0.1.2.dist-info/LICENSE
cogrid-0.1.2.dist-info/METADATA
cogrid-0.1.2.dist-info/WHEEL
cogrid-0.1.2.dist-info/top_level.txt
cogrid-0.1.2.dist-info/RECORD
